{
  "version": "1.0.0",
  "format": "UPFS",
  "name": "Vintage Lead",
  "author": "Bret Bouchard",
  "description": "Warm vintage lead with slight detune, soft filter, and chorus for that classic polysynth feel.",
  "instrument": "Unknown",
  "platform": "universal",
  "creationDate": "2026-01-21T18:48:01.851552",
  "categories": [
    "Lead"
  ],
  "tags": [
    "lead",
    "vintage",
    "warm",
    "polysynth",
    "classic"
  ],
  "parameters": {
    "osc1.waveform": 0.0,
    "osc1.pitch": 0.5,
    "osc1.detune": 0.495,
    "osc1.level": 0.75,
    "osc2.waveform": 1.0,
    "osc2.pitch": 0.5,
    "osc2.detune": 0.505,
    "osc2.level": 0.75,
    "filter.type": 0.0,
    "filter.cutoff": 0.5,
    "filter.resonance": 0.2,
    "filter.env.amount": 0.25,
    "filter.lfo.rate": 0.5,
    "filter.lfo.amount": 0.0,
    "env.adsr.a": 0.012,
    "env.adsr.d": 0.18,
    "env.adsr.s": 0.55,
    "env.adsr.r": 0.28,
    "fx.drive": 0.05,
    "fx.chorus": 0.45,
    "fx.delay": 0.12,
    "fx.reverb": 0.3,
    "output.level": 0.8,
    "output.pan": 0.5
  },
  "macros": {},
  "modulationMatrix": [],
  "metadata": {
    "sourceFile": "/Users/bretbouchard/apps/schill/white_room/juce_backend/instruments/presets/LocalGal/16_Lead_Vintage.json",
    "conversionDate": "2026-01-21T18:48:01.851544",
    "originalFormat": "Legacy JSON",
    "converterVersion": "1.0.0",
    "originalVersion": "1.0.0"
  }
}