{
  "version": "1.0.0",
  "format": "UPFS",
  "name": "FX Alien",
  "author": "Bret Bouchard",
  "description": "Sci-fi alien texture with ring modulation, LFO filter, and metallic overtones.",
  "instrument": "Unknown",
  "platform": "universal",
  "creationDate": "2026-01-21T18:48:03.792229",
  "categories": [
    "FX"
  ],
  "tags": [
    "FX",
    "alien",
    "sci-fi",
    "metallic",
    "texture"
  ],
  "parameters": {
    "osc1.waveform": 2.0,
    "osc1.pitch": 0.5,
    "osc1.detune": 0.5,
    "osc1.level": 0.7,
    "osc2.waveform": 2.0,
    "osc2.pitch": 0.5,
    "osc2.detune": 0.45,
    "osc2.level": 0.7,
    "filter.type": 0.0,
    "filter.cutoff": 0.5,
    "filter.resonance": 0.5,
    "filter.env.amount": 0.2,
    "filter.lfo.rate": 0.35,
    "filter.lfo.amount": 0.5,
    "env.adsr.a": 0.05,
    "env.adsr.d": 0.3,
    "env.adsr.s": 0.6,
    "env.adsr.r": 0.4,
    "fx.drive": 0.15,
    "fx.chorus": 0.55,
    "fx.delay": 0.3,
    "fx.reverb": 0.6,
    "output.level": 0.72,
    "output.pan": 0.5
  },
  "macros": {},
  "modulationMatrix": [],
  "metadata": {
    "sourceFile": "/Users/bretbouchard/apps/schill/white_room/juce_backend/instruments/presets/LocalGal/32_FX_Alien.json",
    "conversionDate": "2026-01-21T18:48:03.792222",
    "originalFormat": "Legacy JSON",
    "converterVersion": "1.0.0",
    "originalVersion": "1.0.0"
  }
}